autodistill_efficient_yolo_world/__init__.py
autodistill_efficient_yolo_world/model.py
autodistill_efficient_yolo_world-0.1.1.dist-info/METADATA
autodistill_efficient_yolo_world-0.1.1.dist-info/WHEEL
autodistill_efficient_yolo_world-0.1.1.dist-info/top_level.txt
autodistill_efficient_yolo_world-0.1.1.dist-info/RECORD
