Metadata-Version: 2.1
Name: autodistill-efficient-yolo-world
Version: 0.1.1
Summary: EfficientSAM + YOLO-World base model for use with Autodistill
Home-page: https://github.com/roboflow/autodistill-efficient-yolo-world
Author: Roboflow
Author-email: support@roboflow.com
Classifier: Programming Language :: Python :: 3
Classifier: Operating System :: OS Independent
Requires-Python: >=3.7
Requires-Dist: supervision
Requires-Dist: autodistill-yolo-world
Requires-Dist: autodistill-efficientsam
Requires-Dist: numpy
Requires-Dist: torch
Provides-Extra: dev
Requires-Dist: flake8 ; extra == 'dev'
Requires-Dist: black ==22.3.0 ; extra == 'dev'
Requires-Dist: isort ; extra == 'dev'
Requires-Dist: twine ; extra == 'dev'
Requires-Dist: pytest ; extra == 'dev'
Requires-Dist: wheel ; extra == 'dev'
